swamid_plugins/__init__.py
swamid_plugins/accr/__init__.py
swamid_plugins/assurance/__init__.py
swamid_plugins/assurance/service.py
swamid_plugins/assurance/swamid.py
swamid_plugins/attribute_injector/__init__.py
swamid_plugins/attributes/__init__.py
swamid_plugins/audit_log/__init__.py
swamid_plugins/eppn_mapper/__init__.py
swamid_plugins/epsa_constructor/__init__.py
swamid_plugins/healthcheck/__init__.py
swamid_plugins/metainfo/__init__.py
swamid_plugins/metainfo/metainfo.py
swamid_plugins/metainfo/metainfo_old.py
swamid_plugins/metainfo/collectors/__init__.py
swamid_plugins/metainfo/collectors/oidc.py
swamid_plugins/metainfo/collectors/saml.py
swamid_plugins/mfa/__init__.py
swamid_plugins/profiler/__init__.py
swamid_plugins/scope_filter/__init__.py
swamid_plugins/site_selector/__init__.py
swamid_plugins-0.2.0.dist-info/METADATA
swamid_plugins-0.2.0.dist-info/WHEEL
swamid_plugins-0.2.0.dist-info/top_level.txt
swamid_plugins-0.2.0.dist-info/RECORD
