Metadata-Version: 2.4
Name: swamid-plugins
Version: 0.2.0
Summary: swamid plugins for the satosa proxy
License: Apache License Version 2.0
Requires-Dist: SATOSA>=7.0.3
Requires-Dist: Jinja2
